{
 "actions": [],
 "allow_rename": 1,
 "creation": "2025-06-21 01:23:27.586555",
 "doctype": "DocType",
 "editable_grid": 1,
 "engine": "InnoDB",
 "field_order": [
  "status",
  "incoming_message",
  "incoming_message_time",
  "outgoing_message",
  "outgoing_message_time",
  "response_time_in_seconds",
  "user"
 ],
 "fields": [
  {
   "fieldname": "status",
   "fieldtype": "Link",
   "in_list_view": 1,
   "label": "Status",
   "options": "Messenger Conversation Status"
  },
  {
   "fieldname": "incoming_message",
   "fieldtype": "Link",
   "in_list_view": 1,
   "label": "Incoming Message",
   "options": "Messenger Message"
  },
  {
   "fieldname": "outgoing_message",
   "fieldtype": "Link",
   "in_list_view": 1,
   "label": "Outgoing Message",
   "options": "Messenger Message"
  },
  {
   "fieldname": "response_time_in_seconds",
   "fieldtype": "Float",
   "in_list_view": 1,
   "label": "Response Time (in seconds)"
  },
  {
   "fieldname": "user",
   "fieldtype": "Link",
   "in_list_view": 1,
   "label": "User",
   "options": "User"
  },
  {
   "fieldname": "incoming_message_time",
   "fieldtype": "Datetime",
   "label": "Incoming Message Time"
  },
  {
   "fieldname": "outgoing_message_time",
   "fieldtype": "Datetime",
   "label": "Outgoing Message Time"
  }
 ],
 "grid_page_length": 50,
 "index_web_pages_for_search": 1,
 "istable": 1,
 "links": [],
 "modified": "2025-06-23 19:09:23.241589",
 "modified_by": "Administrator",
 "module": "Frappe Messenger",
 "name": "Messenger First Response Details",
 "owner": "Administrator",
 "permissions": [],
 "row_format": "Dynamic",
 "sort_field": "modified",
 "sort_order": "DESC",
 "states": []
}